{
    "reflection": [
        "reflection",
        "Reflektion",
        "Reflection"
    ],
    "vehicle": [
        "vehicle",
        "Fahrzeug",
        "Vehicle"
    ],
    "bump": [
        "bump",
        "Dent/Bump",
        "dent_bump",
        "Delle",
        "Deformation",
        "Verformung",
        "deformation"
    ],
    "corrosion": [
        "corrosion",
        "Korrosion",
        "Corrosion"
    ],
    "scratch": [
        "scratch",
        "Kratzer",
        "Scratch"
    ],
    "crack": [
        "crack",
        "Riss",
        "Crack"
    ],
    "dirt": [
        "dirt",
        "Dirt",
        "Verschmutzung"
    ],
    "rim_damage": [
        "rim_damage",
        "Felgenschaden",
        "Rim damage",
        "Bordsteinschaden"
    ],
    "misc": [
        "misc",
        "Sonstiges",
        "Miscellaneous (Misc)"
    ]
}
