{
    "Pixels": {
        "x": 157,
        "y": 376
    },
    "imageData": null,
    "imageHeight": 3000,
    "imagePath": "2020-07-18+17-24-04+ALU4567-Seite+Links+Unten-_00116.jpg",
    "imageWidth": 4096,
    "shapes": [
        {
            "label": "Scratch",
            "points": [
                [
                    1416.2501067401822,
                    2072.2239804920678
                ],
                [
                    1389.8603531984397,
                    2097.775964080104
                ],
                [
                    1430.9110809300391,
                    2095.262654218986
                ],
                [
                    1447.6664800041615,
                    2071.386210538362
                ]
            ],
            "shape_type": "polygon"
        },
        {
            "label": "Vehicle",
            "points": [
                [
                    0,
                    2208.0624187256167
                ],
                [
                    4072.8218465539644,
                    2184.6553966189845
                ],
                [
                    4081.5994798439506,
                    4.876462938881661
                ],
                [
                    14.629388816644983,
                    9.752925877763323
                ]
            ],
            "shape_type": "polygon"
        }
    ]
}
