{
  "version": "3.21.1",
  "flags": {},
  "shapes": [
    {
      "label": "dent_bump",
      "line_color": null,
      "fill_color": null,
      "points": [
        [
          2181.159420289855,
          786.9565217391304
        ],
        [
          2121.7391304347825,
          878.2608695652173
        ],
        [
          2142.028985507246,
          926.086956521739
        ],
        [
          2247.8260869565215,
          982.6086956521739
        ],
        [
          2314.492753623188,
          991.3043478260869
        ],
        [
          2353.623188405797,
          959.4202898550724
        ],
        [
          2407.246376811594,
          989.855072463768
        ],
        [
          2431.8840579710145,
          978.2608695652173
        ],
        [
          2415.942028985507,
          888.4057971014493
        ],
        [
          2328.9855072463765,
          785.5072463768115
        ],
        [
          2228.9855072463765,
          771.0144927536231
        ]
      ],
      "shape_type": "polygon",
      "flags": {}
    },
    {
      "label": "crack",
      "line_color": null,
      "fill_color": null,
      "points": [
        [
          1727.5362318840578,
          1198.550724637681
        ],
        [
          1743.478260869565,
          1240.5797101449275
        ],
        [
          1782.6086956521738,
          1234.782608695652
        ],
        [
          1817.391304347826,
          1273.9130434782608
        ],
        [
          1891.3043478260868,
          1375.3623188405795
        ],
        [
          1866.6666666666665,
          1394.2028985507245
        ],
        [
          1810.1449275362318,
          1386.9565217391303
        ],
        [
          1753.623188405797,
          1407.246376811594
        ],
        [
          1679.710144927536,
          1392.7536231884058
        ],
        [
          1695.6521739130433,
          1320.2898550724638
        ]
      ],
      "shape_type": "polygon",
      "flags": {}
    },
    {
      "label": "scratch",
      "line_color": null,
      "fill_color": null,
      "points": [
        [
          1803.030303030303,
          1583.8383838383838
        ],
        [
          1830.3030303030303,
          1573.7373737373737
        ],
        [
          1843.4343434343434,
          1605.050505050505
        ],
        [
          1793.939393939394,
          1620.2020202020203
        ],
        [
          1779.79797979798,
          1603.030303030303
        ]
      ],
      "shape_type": "polygon",
      "flags": {}
    },
    {
      "label": "misc",
      "line_color": null,
      "fill_color": null,
      "points": [
        [
          1892.2480620155038,
          679.8449612403101
        ],
        [
          1924.031007751938,
          804.6511627906976
        ],
        [
          1949.612403100775,
          833.3333333333333
        ],
        [
          1974.4186046511627,
          849.6124031007752
        ],
        [
          2231.0077519379843,
          985.2713178294573
        ],
        [
          2238.7596899224804,
          982.9457364341085
        ],
        [
          1991.4728682170542,
          855.813953488372
        ],
        [
          1952.7131782945735,
          828.6821705426356
        ],
        [
          1926.3565891472867,
          793.0232558139535
        ]
      ],
      "shape_type": "polygon",
      "flags": {}
    },
    {
      "label": "misc",
      "line_color": null,
      "fill_color": null,
      "points": [
        [
          2279.84496124031,
          1003.8759689922481
        ],
        [
          2196.124031007752,
          990.6976744186046
        ],
        [
          2061.240310077519,
          976.7441860465116
        ],
        [
          2061.240310077519,
          987.5968992248062
        ],
        [
          2269.767441860465,
          1013.953488372093
        ]
      ],
      "shape_type": "polygon",
      "flags": {}
    },
    {
      "label": "scratch",
      "line_color": null,
      "fill_color": null,
      "points": [
        [
          1991.6666666666665,
          652.7777777777777
        ],
        [
          2016.6666666666665,
          667.5925925925925
        ],
        [
          2022.2222222222222,
          663.8888888888888
        ],
        [
          2000.9259259259259,
          649.074074074074
        ]
      ],
      "shape_type": "polygon",
      "flags": {}
    }
  ],
  "lineColor": [
    0,
    255,
    0,
    128
  ],
  "fillColor": [
    255,
    0,
    0,
    128
  ],
  "imagePath": "2020-04-27+14-34-27+N0M786-Heck+Nah+Rechts-_00030.jpg",
  "imageData": null,
  "imageHeight": 3000,
  "imageWidth": 4096
}