{
    "Pixels": {
        "x": 330,
        "y": 315
    },
    "imageData": null,
    "imageHeight": 3000,
    "imagePath": "2020-07-18+17-24-04+ALU4567-Heck+Weit+Links-_00044.jpg",
    "imageWidth": 4096,
    "shapes": [
        {
            "label": "Scratch",
            "points": [
                [
                    1608.8186357371146,
                    1775.1806601138235
                ],
                [
                    1626.4334383181779,
                    1800.9504638898234
                ],
                [
                    1641.764840564659,
                    1789.2072621691145
                ],
                [
                    1640.460040373469,
                    1774.202059970431
                ]
            ],
            "shape_type": "polygon"
        },
        {
            "label": "Vehicle",
            "points": [
                [
                    308.5998987341769,
                    1493.2253164556948
                ],
                [
                    314.5727999999997,
                    1555.9407797468339
                ],
                [
                    314.5727999999997,
                    1612.6833417721502
                ],
                [
                    332.491503797468,
                    1734.1323341772136
                ],
                [
                    362.3560101265819,
                    1766.9832911392389
                ],
                [
                    511.6785417721514,
                    1768.9742582278463
                ],
                [
                    526.6107949367083,
                    1737.118784810125
                ],
                [
                    536.5656303797463,
                    1687.344607594935
                ],
                [
                    716.7481518987335,
                    1731.145883544302
                ],
                [
                    893.9442227848092,
                    1790.87489620253
                ],
                [
                    952.6777518987333,
                    1975.0393518987323
                ],
                [
                    978.560324050632,
                    1998.9309569620234
                ],
                [
                    1022.8593417721506,
                    2029.5420759493647
                ],
                [
                    1086.3214177215177,
                    2041.985620253162
                ],
                [
                    1291.6398987341756,
                    2017.0985316455672
                ],
                [
                    1332.7035949367073,
                    1958.613873417719
                ],
                [
                    1371.2785822784795,
                    1859.0655189873396
                ],
                [
                    1658.7244556962005,
                    1824.2235949367066
                ],
                [
                    1785.6486075949347,
                    1818.001822784808
                ],
                [
                    1867.7759999999978,
                    1814.2687594936688
                ],
                [
                    1912.5727594936686,
                    1831.6897215189852
                ],
                [
                    1920.0388860759472,
                    1831.6897215189852
                ],
                [
                    1983.500962025314,
                    1816.7574683544283
                ],
                [
                    2838.683544303794,
                    1753.7620253164537
                ],
                [
                    3023.3924050632877,
                    1714.8759493670866
                ],
                [
                    3040.8911392405025,
                    1633.2151898734157
                ],
                [
                    3079.77721518987,
                    1530.167088607593
                ],
                [
                    3071.9999999999964,
                    1469.8936708860742
                ],
                [
                    3093.3873417721484,
                    1353.235443037973
                ],
                [
                    3033.1139240506295,
                    1232.6886075949353
                ],
                [
                    2986.4506329113888,
                    1088.8101265822772
                ],
                [
                    2935.8987341772117,
                    1024.6481012658217
                ],
                [
                    2862.532841316451,
                    923.1716196455682
                ],
                [
                    2789.265252455692,
                    869.6544243037961
                ],
                [
                    2674.5855481518947,
                    828.8794183291126
                ],
                [
                    2424.2015270886036,
                    788.7415218227836
                ],
                [
                    2377.692535898729,
                    789.3786312911376
                ],
                [
                    2136.865156860755,
                    676.6102553924037
                ],
                [
                    2003.7092779746795,
                    638.3836872911379
                ],
                [
                    1845.0690203544266,
                    610.350870683543
                ],
                [
                    1440.962430379743,
                    569.9143291139226
                ],
                [
                    1159.738329113921,
                    569.9143291139226
                ],
                [
                    1000.4609620253138,
                    644.5755949367071
                ],
                [
                    839.9392405063269,
                    734.1691139240487
                ],
                [
                    722.969924050631,
                    842.4279493670864
                ],
                [
                    623.4215696202515,
                    970.5964556962
                ],
                [
                    598.5344810126567,
                    1002.9496708860734
                ],
                [
                    577.380455696201,
                    1002.9496708860734
                ],
                [
                    563.6925569620238,
                    986.7730632911366
                ],
                [
                    547.5159493670872,
                    975.5738734177189
                ],
                [
                    431.79098734177103,
                    991.7504810126557
                ],
                [
                    403.17083544303694,
                    1021.6149873417695
                ],
                [
                    413.1256708860749,
                    1068.9004556961997
                ],
                [
                    451.70065822784693,
                    1100.0093164556934
                ],
                [
                    501.4748354430367,
                    1106.231088607592
                ],
                [
                    557.4707848101251,
                    1102.4980253164529
                ],
                [
                    500.2304810126569,
                    1147.2947848101235
                ],
                [
                    411.8813164556951,
                    1200.8020253164525
                ],
                [
                    332.2426329113915,
                    1290.3955443037942
                ],
                [
                    306.11118987341695,
                    1352.6132658227814
                ]
            ],
            "shape_type": "polygon"
        }
    ]
}
