{
  "version": "3.21.1",
  "flags": {},
  "shapes": [
    {
      "label": "Fahrzeug",
      "line_color": null,
      "fill_color": null,
      "points": [
        [
          7.5,
          4.0
        ],
        [
          1973.125,
          7.125
        ],
        [
          2020.0,
          69.625
        ],
        [
          2098.125,
          216.5
        ],
        [
          2148.125,
          338.375
        ],
        [
          2185.625,
          497.75
        ],
        [
          2207.5,
          679.0
        ],
        [
          2204.375,
          835.25
        ],
        [
          2257.5,
          904.0
        ],
        [
          2338.75,
          979.0
        ],
        [
          2379.375,
          1063.375
        ],
        [
          2370.0,
          1163.375
        ],
        [
          2348.125,
          1260.25
        ],
        [
          2316.875,
          1413.375
        ],
        [
          2285.625,
          1494.625
        ],
        [
          2323.125,
          1557.125
        ],
        [
          2301.25,
          1619.625
        ],
        [
          2241.875,
          1675.875
        ],
        [
          2241.875,
          1735.25
        ],
        [
          2205.3333333333335,
          1817.3333333333333
        ],
        [
          2177.3333333333335,
          1849.3333333333333
        ],
        [
          1913.3333333333333,
          1866.6666666666667
        ],
        [
          1717.3333333333333,
          1881.3333333333333
        ],
        [
          1648.0,
          1892.0
        ],
        [
          1636.0,
          1856.0
        ],
        [
          1005.3333333333334,
          2001.3333333333333
        ],
        [
          965.3333333333334,
          2024.0
        ],
        [
          869.3333333333334,
          2049.3333333333335
        ],
        [
          829.3333333333334,
          2040.0
        ],
        [
          317.3333333333333,
          2153.3333333333335
        ],
        [
          285.3333333333333,
          2102.6666666666665
        ],
        [
          217.33333333333334,
          2108.0
        ],
        [
          156.0,
          2241.3333333333335
        ],
        [
          0,
          2482
        ]
      ],
      "shape_type": "polygon",
      "flags": {}
    },
    {
      "label": "Kratzer",
      "line_color": null,
      "fill_color": null,
      "points": [
        [
          1988.1355932203392,
          1127.9661016949153
        ],
        [
          2105.084745762712,
          1127.9661016949153
        ],
        [
          2100.0,
          1142.3728813559323
        ],
        [
          1991.5254237288136,
          1149.1525423728815
        ],
        [
          1977.1186440677968,
          1134.7457627118645
        ]
      ],
      "shape_type": "polygon",
      "flags": {}
    },
    {
      "label": "misc",
      "line_color": null,
      "fill_color": null,
      "points": [
        [
          1922.8813559322034,
          933.0508474576271
        ],
        [
          1962.7118644067798,
          924.5762711864407
        ],
        [
          2005.084745762712,
          931.3559322033899
        ],
        [
          2051.6949152542375,
          950.8474576271187
        ],
        [
          2088.135593220339,
          987.2881355932204
        ],
        [
          2102.542372881356,
          1011.0169491525425
        ],
        [
          2072.0338983050847,
          1033.8983050847457
        ],
        [
          2016.949152542373,
          1046.6101694915255
        ],
        [
          1979.6610169491526,
          1056.7796610169491
        ],
        [
          1933.898305084746,
          1065.2542372881358
        ],
        [
          1941.5254237288136,
          1051.6949152542372
        ],
        [
          1983.0508474576272,
          1041.5254237288136
        ],
        [
          1987.2881355932204,
          1024.5762711864406
        ],
        [
          2077.1186440677966,
          1007.6271186440679
        ],
        [
          2049.1525423728813,
          975.4237288135594
        ],
        [
          1982.2033898305085,
          950.8474576271187
        ]
      ],
      "shape_type": "polygon",
      "flags": {}
    },
    {
      "label": "reflection",
      "line_color": null,
      "fill_color": null,
      "points": [
        [
          2000.0,
          954.2372881355933
        ],
        [
          2022.8813559322034,
          954.2372881355933
        ],
        [
          2032.2033898305085,
          999.1525423728814
        ],
        [
          2027.1186440677968,
          1066.949152542373
        ],
        [
          2012.7118644067798,
          1131.3559322033898
        ],
        [
          1984.7457627118645,
          1131.3559322033898
        ],
        [
          1995.7627118644068,
          1093.2203389830509
        ],
        [
          2011.0169491525426,
          1026.271186440678
        ],
        [
          2002.542372881356,
          976.271186440678
        ]
      ],
      "shape_type": "polygon",
      "flags": {}
    }
  ],
  "lineColor": [
    0,
    255,
    0,
    128
  ],
  "fillColor": [
    255,
    0,
    0,
    128
  ],
  "imagePath": "2020-04-21+14-29-28+NAB448-Seite+Links+Unten-_00122.jpg",
  "imageData": null,
  "imageHeight": 3000,
  "imageWidth": 4096
}