{
  "version": "3.21.1",
  "flags": {},
  "shapes": [
    {
      "label": "scratch",
      "line_color": null,
      "fill_color": null,
      "points": [
        [
          2507.4074074074074,
          411.1111111111111
        ],
        [
          3067.5925925925926,
          414.8148148148148
        ],
        [
          3061.111111111111,
          422.2222222222222
        ],
        [
          2505.555555555555,
          424.074074074074
        ]
      ],
      "shape_type": "polygon",
      "flags": {}
    },
    {
      "label": "corrosion",
      "line_color": null,
      "fill_color": null,
      "points": [
        [
          2111.111111111111,
          1799.9999999999998
        ],
        [
          2147.222222222222,
          1776.8518518518517
        ],
        [
          2154.6296296296296,
          1790.7407407407406
        ],
        [
          2119.4444444444443,
          1813.8888888888887
        ]
      ],
      "shape_type": "polygon",
      "flags": {}
    },
    {
      "label": "corrosion",
      "line_color": null,
      "fill_color": null,
      "points": [
        [
          2163.8888888888887,
          1613.8888888888887
        ],
        [
          2183.333333333333,
          1620.3703703703702
        ],
        [
          2194.4444444444443,
          1649.074074074074
        ],
        [
          2185.185185185185,
          1656.4814814814813
        ],
        [
          2162.962962962963,
          1635.185185185185
        ]
      ],
      "shape_type": "polygon",
      "flags": {}
    },
    {
      "label": "corrosion",
      "line_color": null,
      "fill_color": null,
      "points": [
        [
          2194.4444444444443,
          2014.8148148148148
        ],
        [
          2250.9259259259256,
          2006.4814814814813
        ],
        [
          2202.777777777778,
          2062.962962962963
        ],
        [
          2195.3703703703704,
          2032.4074074074072
        ],
        [
          2214.814814814815,
          2031.4814814814813
        ],
        [
          2216.6666666666665,
          2023.148148148148
        ],
        [
          2189.814814814815,
          2025.9259259259259
        ]
      ],
      "shape_type": "polygon",
      "flags": {}
    },
    {
      "label": "corrosion",
      "line_color": null,
      "fill_color": null,
      "points": [
        [
          1786.111111111111,
          1956.4814814814813
        ],
        [
          1801.8518518518517,
          1971.296296296296
        ],
        [
          1833.3333333333333,
          1974.9999999999998
        ],
        [
          1812.9629629629628,
          2006.4814814814813
        ],
        [
          1808.3333333333333,
          2011.111111111111
        ],
        [
          1797.2222222222222,
          1999.074074074074
        ],
        [
          1804.6296296296296,
          1981.4814814814813
        ],
        [
          1793.5185185185185,
          1984.2592592592591
        ],
        [
          1781.4814814814813,
          1972.2222222222222
        ],
        [
          1770.3703703703702,
          1967.5925925925924
        ]
      ],
      "shape_type": "polygon",
      "flags": {}
    },
    {
      "label": "corrosion",
      "line_color": null,
      "fill_color": null,
      "points": [
        [
          1675.0,
          1535.185185185185
        ],
        [
          1684.2592592592591,
          1541.6666666666665
        ],
        [
          1698.148148148148,
          1582.4074074074074
        ],
        [
          1696.296296296296,
          1588.8888888888887
        ],
        [
          1676.8518518518517,
          1590.7407407407406
        ],
        [
          1673.148148148148,
          1600.9259259259259
        ],
        [
          1653.7037037037037,
          1600.0
        ],
        [
          1664.8148148148148,
          1529.6296296296296
        ]
      ],
      "shape_type": "polygon",
      "flags": {}
    },
    {
      "label": "dirt",
      "line_color": null,
      "fill_color": null,
      "points": [
        [
          552.875,
          1679.0
        ],
        [
          652.875,
          1650.875
        ],
        [
          752.875,
          1600.875
        ],
        [
          796.625,
          1597.75
        ],
        [
          906.0,
          1425.875
        ],
        [
          940.375,
          1422.75
        ],
        [
          906.0,
          1516.5
        ],
        [
          862.25,
          1604.0
        ],
        [
          790.375,
          1666.5
        ],
        [
          643.5,
          1707.125
        ],
        [
          524.75,
          1725.875
        ]
      ],
      "shape_type": "polygon",
      "flags": {}
    },
    {
      "label": "corrosion",
      "line_color": null,
      "fill_color": null,
      "points": [
        [
          1541.111111111111,
          1763.3333333333333
        ],
        [
          1555.5555555555554,
          1768.888888888889
        ],
        [
          1561.111111111111,
          1795.5555555555554
        ],
        [
          1572.2222222222222,
          1804.4444444444443
        ],
        [
          1573.3333333333333,
          1826.6666666666665
        ],
        [
          1553.3333333333333,
          1845.5555555555554
        ],
        [
          1543.3333333333333,
          1814.4444444444443
        ],
        [
          1547.7777777777778,
          1798.888888888889
        ],
        [
          1547.7777777777778,
          1787.7777777777778
        ]
      ],
      "shape_type": "polygon",
      "flags": {}
    },
    {
      "label": "corrosion",
      "line_color": null,
      "fill_color": null,
      "points": [
        [
          1787.7777777777778,
          2115.5555555555557
        ],
        [
          1771.111111111111,
          2150.0
        ],
        [
          1831.111111111111,
          2180.0
        ],
        [
          1831.111111111111,
          2158.8888888888887
        ],
        [
          1817.7777777777778,
          2154.4444444444443
        ],
        [
          1825.5555555555554,
          2134.4444444444443
        ]
      ],
      "shape_type": "polygon",
      "flags": {}
    },
    {
      "label": "corrosion",
      "line_color": null,
      "fill_color": null,
      "points": [
        [
          2150.0,
          2171.111111111111
        ],
        [
          2213.3333333333335,
          2152.222222222222
        ],
        [
          2213.3333333333335,
          2163.3333333333335
        ],
        [
          2228.8888888888887,
          2185.5555555555557
        ],
        [
          2151.111111111111,
          2202.222222222222
        ]
      ],
      "shape_type": "polygon",
      "flags": {}
    },
    {
      "label": "corrosion",
      "line_color": null,
      "fill_color": null,
      "points": [
        [
          1585.5555555555554,
          1423.3333333333333
        ],
        [
          1563.3333333333333,
          1471.111111111111
        ],
        [
          1603.3333333333333,
          1475.5555555555554
        ],
        [
          1627.7777777777778,
          1434.4444444444443
        ]
      ],
      "shape_type": "polygon",
      "flags": {}
    }
  ],
  "lineColor": [
    0,
    255,
    0,
    128
  ],
  "fillColor": [
    255,
    0,
    0,
    128
  ],
  "imagePath": "2020-04-15+14-09-51+N0X758-Seite+Rechts+Unten-_00051.jpg",
  "imageData": null,
  "imageHeight": 3000,
  "imageWidth": 4096
}