{
  "version": "3.21.1",
  "flags": {},
  "shapes": [
    {
      "label": "Fahrzeug",
      "line_color": null,
      "fill_color": null,
      "points": [
        [
          2843.5,
          4.0
        ],
        [
          4095,
          4
        ],
        [
          4095,
          2516
        ],
        [
          3890.375,
          2363.375
        ],
        [
          3693.5,
          2088.375
        ],
        [
          3612.6984126984125,
          2147.6190476190477
        ],
        [
          3631.746031746032,
          2330.15873015873
        ],
        [
          3619.047619047619,
          2360.3174603174602
        ],
        [
          3449.2063492063494,
          2292.063492063492
        ],
        [
          3365.079365079365,
          2230.15873015873
        ],
        [
          3331.746031746032,
          2168.253968253968
        ],
        [
          3077.777777777778,
          2139.6825396825398
        ],
        [
          2988.8888888888887,
          2112.6984126984125
        ],
        [
          2649.2063492063494,
          2049.2063492063494
        ],
        [
          2157.1428571428573,
          1930.1587301587301
        ],
        [
          2066.6666666666665,
          1876.1904761904761
        ],
        [
          2031.7460317460318,
          1807.936507936508
        ],
        [
          1985.7142857142858,
          1800.0
        ],
        [
          1904.7619047619048,
          1761.904761904762
        ],
        [
          1755.5555555555557,
          1679.3650793650793
        ],
        [
          1761.904761904762,
          1657.142857142857
        ],
        [
          1825.3968253968253,
          1609.5238095238094
        ],
        [
          1760.3174603174602,
          1576.1904761904761
        ],
        [
          1768.2539682539682,
          1566.6666666666667
        ],
        [
          1760.3174603174602,
          1555.5555555555557
        ],
        [
          1780.952380952381,
          1528.5714285714287
        ],
        [
          1760.3174603174602,
          1511.111111111111
        ],
        [
          1757.142857142857,
          1479.3650793650793
        ],
        [
          1761.904761904762,
          1461.904761904762
        ],
        [
          1722.2222222222222,
          1239.6825396825398
        ],
        [
          1761.904761904762,
          1215.873015873016
        ],
        [
          1817.4603174603174,
          1165.079365079365
        ],
        [
          1758.7301587301588,
          1134.920634920635
        ],
        [
          1766.6666666666667,
          1038.095238095238
        ],
        [
          1746.031746031746,
          942.8571428571429
        ],
        [
          1798.4126984126983,
          782.5396825396825
        ],
        [
          1798.4126984126983,
          753.968253968254
        ],
        [
          1807.936507936508,
          744.4444444444445
        ],
        [
          1795.2380952380952,
          671.4285714285714
        ],
        [
          1857.142857142857,
          585.7142857142857
        ],
        [
          1941.2698412698412,
          485.7142857142857
        ],
        [
          2012.6984126984128,
          417.46031746031747
        ],
        [
          2165.0793650793653,
          293.6507936507937
        ],
        [
          2293.6507936507937,
          228.57142857142858
        ],
        [
          2558.7301587301586,
          104.76190476190476
        ]
      ],
      "shape_type": "polygon",
      "flags": {}
    },
    {
      "label": "Kratzer",
      "line_color": null,
      "fill_color": null,
      "points": [
        [
          2652.875,
          1150.875
        ],
        [
          2715.375,
          1197.75
        ],
        [
          2793.5,
          1266.5
        ],
        [
          2896.625,
          1357.125
        ],
        [
          3018.5,
          1485.25
        ],
        [
          3052.875,
          1479.0
        ],
        [
          2952.875,
          1372.75
        ],
        [
          3002.875,
          1366.5
        ],
        [
          3065.375,
          1404.0
        ],
        [
          3196.625,
          1400.875
        ],
        [
          3087.25,
          1325.875
        ],
        [
          3212.25,
          1300.875
        ],
        [
          3234.125,
          1238.375
        ],
        [
          3384.125,
          1182.125
        ],
        [
          3652.875,
          1185.25
        ],
        [
          3815.375,
          860.25
        ],
        [
          3809.125,
          819.625
        ],
        [
          3674.75,
          847.75
        ],
        [
          3506.0,
          847.75
        ],
        [
          3349.75,
          829.0
        ],
        [
          3306.0,
          719.625
        ],
        [
          3124.75,
          729.0
        ],
        [
          3152.875,
          766.5
        ],
        [
          3102.875,
          816.5
        ],
        [
          2890.375,
          854.0
        ],
        [
          2906.0,
          875.875
        ],
        [
          2990.375,
          866.5
        ],
        [
          2937.25,
          907.125
        ],
        [
          2896.625,
          979.0
        ],
        [
          2706.0,
          1063.375
        ],
        [
          2643.5,
          1110.25
        ]
      ],
      "shape_type": "polygon",
      "flags": {}
    },
    {
      "label": "Kratzer",
      "line_color": null,
      "fill_color": null,
      "points": [
        [
          2546.666666666667,
          1968.3333333333335
        ],
        [
          2885.0,
          1996.6666666666667
        ],
        [
          3113.3333333333335,
          2003.3333333333335
        ],
        [
          3130.0,
          1983.3333333333335
        ],
        [
          2868.3333333333335,
          1968.3333333333335
        ],
        [
          2785.0,
          1911.6666666666667
        ],
        [
          2698.3333333333335,
          1940.0
        ],
        [
          2533.3333333333335,
          1911.6666666666667
        ]
      ],
      "shape_type": "polygon",
      "flags": {}
    },
    {
      "label": "reflection",
      "line_color": null,
      "fill_color": null,
      "points": [
        [
          3203.3333333333335,
          578.3333333333334
        ],
        [
          3191.666666666667,
          608.3333333333334
        ],
        [
          3136.666666666667,
          1030.0
        ],
        [
          3105.0,
          1171.6666666666667
        ],
        [
          3084.5588235294117,
          1227.941176470588
        ],
        [
          3080.1470588235293,
          1273.5294117647059
        ],
        [
          3050.735294117647,
          1263.235294117647
        ],
        [
          3054.411764705882,
          1192.6470588235293
        ],
        [
          3100.735294117647,
          1048.5294117647059
        ],
        [
          3135.2941176470586,
          892.6470588235294
        ],
        [
          3148.529411764706,
          799.9999999999999
        ],
        [
          3174.9999999999995,
          615.4411764705882
        ]
      ],
      "shape_type": "polygon",
      "flags": {}
    },
    {
      "label": "reflection",
      "line_color": null,
      "fill_color": null,
      "points": [
        [
          2908.8235294117644,
          705.1470588235294
        ],
        [
          2919.1176470588234,
          725.735294117647
        ],
        [
          2899.2647058823527,
          785.2941176470588
        ],
        [
          2871.3235294117644,
          866.9117647058823
        ],
        [
          2826.4705882352937,
          949.9999999999999
        ],
        [
          2788.970588235294,
          1019.1176470588234
        ],
        [
          2756.6176470588234,
          1078.6764705882351
        ],
        [
          2723.529411764706,
          1086.0294117647059
        ],
        [
          2755.1470588235293,
          1023.5294117647059
        ],
        [
          2814.705882352941,
          926.470588235294
        ],
        [
          2851.4705882352937,
          844.1176470588234
        ]
      ],
      "shape_type": "polygon",
      "flags": {}
    }
  ],
  "lineColor": [
    0,
    255,
    0,
    128
  ],
  "fillColor": [
    255,
    0,
    0,
    128
  ],
  "imagePath": "2020-03-19+15-31-33+NAB5550-Seite+Links+Unten-_00112.jpg",
  "imageData": null,
  "imageHeight": 3000,
  "imageWidth": 4096
}